supersayan/__init__.py
supersayan/_setup.py
supersayan/logging_config.py
supersayan/core/__init__.py
supersayan/core/bindings.py
supersayan/core/encryption.py
supersayan/core/keygen.py
supersayan/core/types.py
supersayan/julia_backend/Project.toml
supersayan/julia_backend/__init__.py
supersayan/nn/__init__.py
supersayan/nn/convert.py
supersayan/nn/layers/__init__.py
supersayan/nn/layers/conv2d.py
supersayan/nn/layers/linear.py
supersayan/remote/__init__.py
supersayan/remote/client.py
supersayan/remote/server.py
supersayan/remote/socket_utils.py
supersayan-0.1.3.dist-info/licenses/LICENSE
supersayan-0.1.3.dist-info/METADATA
supersayan-0.1.3.dist-info/WHEEL
supersayan-0.1.3.dist-info/entry_points.txt
supersayan-0.1.3.dist-info/top_level.txt
supersayan-0.1.3.dist-info/RECORD
