Metadata-Version: 2.4
Name: supersayan
Version: 0.1.3
Summary: A high-performance Python library for fully homomorphic encryption (FHE) in deep learning, seamlessly integrated with PyTorch.
Author-email: bonsainoodle <3sprix.exe@gmail.com>, franklintra <franklin.tranie@gmail.com>
Project-URL: GitHub, https://github.com/supersayan-labs/supersayan
Keywords: homomorphic-encryption,FHE,deep-learning,pytorch,privacy-preserving,cryptography,neural-networks,secure-computation,machine-learning,julia
Requires-Python: >=3.9
License-File: LICENSE
Requires-Dist: numpy>=1.24.0
Requires-Dist: torch>=2.0.0
Requires-Dist: julia>=0.6.0
Requires-Dist: uvicorn>=0.20.0
Requires-Dist: fastapi>=0.100.0
Requires-Dist: requests>=2.25.0
Requires-Dist: torchvision>=0.15.0
Requires-Dist: websocket-client>=1.8.0
Requires-Dist: torchsummary>=1.5.1
Requires-Dist: python-socketio>=5.13.0
Requires-Dist: simple-websocket>=1.1.0
Requires-Dist: juliacall>=0.9.25
Provides-Extra: dev
Requires-Dist: pytest>=7.0.0; extra == "dev"
Requires-Dist: pytest-benchmark>=4.0.0; extra == "dev"
Requires-Dist: ruff>=0.4.0; extra == "dev"
Requires-Dist: scalene>=1.5.51; extra == "dev"
Provides-Extra: publish
Requires-Dist: twine>=4.0.0; extra == "publish"
Requires-Dist: build>=0.10.0; extra == "publish"
Dynamic: license-file
